{
"meta":{"test_sets":[],"test_metrics":[],"learn_metrics":[{"best_value":"Min","name":"Logloss"}],"launch_mode":"Train","parameters":"","iteration_count":42,"learn_sets":["learn"],"name":"experiment"},
"iterations":[
{"learn":[0.6005185644],"iteration":0,"passed_time":0.7917957294,"remaining_time":32.4636249},
{"learn":[0.5567317904],"iteration":1,"passed_time":1.364222474,"remaining_time":27.28444947},
{"learn":[0.5290160687],"iteration":2,"passed_time":1.991042409,"remaining_time":25.88355131},
{"learn":[0.5103117814],"iteration":3,"passed_time":2.580841287,"remaining_time":24.51799223},
{"learn":[0.4936670023],"iteration":4,"passed_time":3.15510576,"remaining_time":23.34778262},
{"learn":[0.4804472636],"iteration":5,"passed_time":3.758858335,"remaining_time":22.55315001},
{"learn":[0.4683513991],"iteration":6,"passed_time":4.319843473,"remaining_time":21.59921737},
{"learn":[0.4561247564],"iteration":7,"passed_time":4.905245265,"remaining_time":20.84729238},
{"learn":[0.4460716793],"iteration":8,"passed_time":5.47162743,"remaining_time":20.06263391},
{"learn":[0.4367600244],"iteration":9,"passed_time":6.027027507,"remaining_time":19.28648802},
{"learn":[0.4270225367],"iteration":10,"passed_time":6.583076157,"remaining_time":18.55230553},
{"learn":[0.4202924515],"iteration":11,"passed_time":7.149456595,"remaining_time":17.87364149},
{"learn":[0.4141472454],"iteration":12,"passed_time":7.798268439,"remaining_time":17.39613729},
{"learn":[0.4086591573],"iteration":13,"passed_time":8.437348995,"remaining_time":16.87469799},
{"learn":[0.4024594413],"iteration":14,"passed_time":9.025897463,"remaining_time":16.24661543},
{"learn":[0.3977949534],"iteration":15,"passed_time":9.579449437,"remaining_time":15.56660533},
{"learn":[0.3932913535],"iteration":16,"passed_time":10.13693003,"remaining_time":14.90725004},
{"learn":[0.3890929242],"iteration":17,"passed_time":10.73889549,"remaining_time":14.31852732},
{"learn":[0.3850762051],"iteration":18,"passed_time":11.29256332,"remaining_time":13.66994507},
{"learn":[0.3805155944],"iteration":19,"passed_time":11.86257533,"remaining_time":13.04883286},
{"learn":[0.3764943456],"iteration":20,"passed_time":12.43085745,"remaining_time":12.43085745},
{"learn":[0.3721255689],"iteration":21,"passed_time":12.98778266,"remaining_time":11.80707514},
{"learn":[0.368062109],"iteration":22,"passed_time":13.60128794,"remaining_time":11.23584656},
{"learn":[0.3640184067],"iteration":23,"passed_time":14.16773435,"remaining_time":10.62580076},
{"learn":[0.3600337993],"iteration":24,"passed_time":14.74677333,"remaining_time":10.02780587},
{"learn":[0.3565064605],"iteration":25,"passed_time":15.30182314,"remaining_time":9.416506546},
{"learn":[0.3529294877],"iteration":26,"passed_time":15.85598291,"remaining_time":8.808879392},
{"learn":[0.3492671808],"iteration":27,"passed_time":16.41247739,"remaining_time":8.206238694},
{"learn":[0.3459183973],"iteration":28,"passed_time":16.97557225,"remaining_time":7.609739286},
{"learn":[0.342692528],"iteration":29,"passed_time":17.542981,"remaining_time":7.017192401},
{"learn":[0.3396616372],"iteration":30,"passed_time":18.09944552,"remaining_time":6.422383894},
{"learn":[0.3369491508],"iteration":31,"passed_time":18.65234317,"remaining_time":5.828857241},
{"learn":[0.3339347512],"iteration":32,"passed_time":19.21673057,"remaining_time":5.240926519},
{"learn":[0.3309261997],"iteration":33,"passed_time":19.79778672,"remaining_time":4.658302757},
{"learn":[0.3279011211],"iteration":34,"passed_time":20.3553629,"remaining_time":4.071072581},
{"learn":[0.3253683057],"iteration":35,"passed_time":20.91231745,"remaining_time":3.485386241},
{"learn":[0.322420211],"iteration":36,"passed_time":21.46636677,"remaining_time":2.900860375},
{"learn":[0.3195267878],"iteration":37,"passed_time":22.02146555,"remaining_time":2.318049005},
{"learn":[0.3172030979],"iteration":38,"passed_time":22.59420359,"remaining_time":1.738015661},
{"learn":[0.3151583881],"iteration":39,"passed_time":23.17861448,"remaining_time":1.158930724},
{"learn":[0.3130200774],"iteration":40,"passed_time":23.74089865,"remaining_time":0.5790463086},
{"learn":[0.3106136941],"iteration":41,"passed_time":24.30272199,"remaining_time":0}
]}